filewave/__init__.py
filewave/filewave.py
filewave-0.0.1.dist-info/METADATA
filewave-0.0.1.dist-info/WHEEL
filewave-0.0.1.dist-info/top_level.txt
filewave-0.0.1.dist-info/RECORD
