Metadata-Version: 2.4
Name: filewave
Version: 0.0.1
Summary: A module for convenient file management
Home-page: 
Author: 66Studio
Author-email: 
Classifier: Programming Language :: Python :: 3
Classifier: License :: OSI Approved :: MIT License
Classifier: Operating System :: OS Independent
Requires-Python: >=3.6
Dynamic: author
Dynamic: classifier
Dynamic: description
Dynamic: description-content-type
Dynamic: requires-python
Dynamic: summary
